LICENSE
MANIFEST.in
README.rst
setup.cfg
setup.py
src/django_view_as.egg-info/PKG-INFO
src/django_view_as.egg-info/SOURCES.txt
src/django_view_as.egg-info/dependency_links.txt
src/django_view_as.egg-info/not-zip-safe
src/django_view_as.egg-info/pbr.json
src/django_view_as.egg-info/requires.txt
src/django_view_as.egg-info/top_level.txt
src/viewas/__init__.py
src/viewas/middleware.py
src/viewas/templates/viewas/header.html