Metadata-Version: 1.0
Name: django-view-as
Version: 0.5.0
Summary: A Django middleware which allows you to view the site on behalf of a user.
Home-page: UNKNOWN
Author: David Cramer
Author-email: dcramer@gmail.com
License: Apache License 2.0
Platform: UNKNOWN
